ckc/__init__.py
ckc/exceptions.py
ckc/fields.py
ckc/logging.py
ckc/models.py
ckc/providers.py
ckc/serializers.py
ckc/management/__init__.py
ckc/management/commands/__init__.py
ckc/management/commands/upload_file.py
testproject/__init__.py
testproject/manage.py
testproject/settings.py
testproject/urls.py
testproject/testapp/__init__.py
testproject/testapp/factories.py
testproject/testapp/misconfigured_serializers.py
testproject/testapp/models.py
testproject/testapp/serializers.py
testproject/testapp/views.py
testproject/testapp/viewsets.py
tests/__init__.py
tests/integration/__init__.py
tests/integration/test_default_user_create_mixin.py
tests/integration/test_exceptions.py
tests/integration/test_factories.py
tests/integration/test_json_model_snapshots.py
tests/integration/test_primary_key_write_serializer_read_field.py
tests/integration/test_soft_delete.py
django_ckc-0.0.10.dist-info/LICENSE
django_ckc-0.0.10.dist-info/METADATA
django_ckc-0.0.10.dist-info/WHEEL
django_ckc-0.0.10.dist-info/top_level.txt
django_ckc-0.0.10.dist-info/RECORD
