Metadata-Version: 2.1
Name: django-ckc
Version: 0.0.10
Summary: tools, utilities, etc. we use across projects @ ckc
Home-page: https://github.com/ckcollab/django-ckc
Author: Eric Carmichael
Author-email: eric@ckcollab.com
Keywords: django
Classifier: Development Status :: 4 - Beta
Classifier: Intended Audience :: Developers
Classifier: Programming Language :: Python :: 3.6
Classifier: Programming Language :: Python :: 3.7
Classifier: Programming Language :: Python :: 3.8
Classifier: Programming Language :: Python :: 3.9
Classifier: Programming Language :: Python :: 3.10
Classifier: Programming Language :: Python :: 3.11
Classifier: Topic :: Software Development
Requires-Python: >=3.6
License-File: LICENSE
